varphi_python_dap/__init__.py
varphi_python_dap/cli.py
varphi_python_dap/compiler.py
varphi_python_dap/lib/__init__.py
varphi_python_dap/lib/debugger.py
varphi_python_dap-1.0.6.dist-info/WHEEL
varphi_python_dap-1.0.6.dist-info/entry_points.txt
varphi_python_dap-1.0.6.dist-info/METADATA
varphi_python_dap-1.0.6.dist-info/RECORD
