Metadata-Version: 2.3
Name: varphi-python-dap
Version: 1.0.6
Summary: An implementation of a Varphi-to-DAP-compliant-Python compiler.
Author: Hassan El-Sheikha
Author-email: Hassan El-Sheikha <hmelsheikha@gmail.com>
Requires-Dist: varphi-python==2.0.6
Requires-Python: >=3.13
